{
  "updated_at": "2026-06-30T14:45:56+09:00",
  "count": 91,
  "items": [
    {
      "id": "ed6eb4cdc32eb3a4",
      "time": "2026-06-30T14:30:00+09:00",
      "code": "2164",
      "company": "地域新聞社",
      "title": "主要株主及び主要株主である筆頭株主の異動に関するお知らせ",
      "pdf_url": "https://www.release.tdnet.info140120260630584697.pdf",
      "exchange": "東証",
      "markets": "",
      "source": "scraper",
      "category": "大株主異動",
      "score": 62,
      "impact": "medium",
      "direction": "unknown",
      "urgent": false,
      "confidence": 65,
      "is_correction": false,
      "tags": [],
      "reasons": [
        "筆頭株主の異動"
      ],
      "summary": "主要株主・親会社の異動。支配構造の変化。",
      "analyzed_by": "rules",
      "analyzed_at": "2026-06-30T14:43:21+09:00"
    },
    {
      "id": "1262622",
      "time": "2026-06-30T14:00:00+09:00",
      "code": "2998",
      "company": "Ｇ－クリアル",
      "title": "借入金の期限前返済に関するお知らせ",
      "pdf_url": "https://webapi.yanoshin.jp/rd.php?https://www.release.tdnet.info/inbs/140120260630584081.pdf",
      "exchange": "東証",
      "markets": "",
      "source": "yanoshin",
      "category": "その他開示",
      "score": 35,
      "impact": "low",
      "direction": "unknown",
      "urgent": false,
      "confidence": 40,
      "is_correction": false,
      "tags": [],
      "reasons": [
        "その他開示"
      ],
      "summary": "定例・補足的な開示。株価への影響は限定的とみられる。",
      "analyzed_by": "rules",
      "analyzed_at": "2026-06-30T14:45:54+09:00"
    },
    {
      "id": "1262623",
      "time": "2026-06-30T14:00:00+09:00",
      "code": "322A",
      "company": "Ｐ－ヒメジ理化",
      "title": "代表取締役の異動に関するお知らせ",
      "pdf_url": "https://webapi.yanoshin.jp/rd.php?https://www.release.tdnet.info/inbs/140120260630584051.pdf",
      "exchange": "東証",
      "markets": "",
      "source": "yanoshin",
      "category": "その他開示",
      "score": 35,
      "impact": "low",
      "direction": "unknown",
      "urgent": false,
      "confidence": 40,
      "is_correction": false,
      "tags": [],
      "reasons": [
        "その他開示"
      ],
      "summary": "定例・補足的な開示。株価への影響は限定的とみられる。",
      "analyzed_by": "rules",
      "analyzed_at": "2026-06-30T14:45:54+09:00"
    },
    {
      "id": "1262629",
      "time": "2026-06-30T14:00:00+09:00",
      "code": "5644",
      "company": "メタルアート",
      "title": "非上場の親会社等の決算情報に関するお知らせ",
      "pdf_url": "https://webapi.yanoshin.jp/rd.php?https://www.release.tdnet.info/inbs/140120260630584424.pdf",
      "exchange": "東証",
      "markets": "",
      "source": "yanoshin",
      "category": "その他開示",
      "score": 35,
      "impact": "low",
      "direction": "unknown",
      "urgent": false,
      "confidence": 40,
      "is_correction": false,
      "tags": [],
      "reasons": [
        "その他開示"
      ],
      "summary": "定例・補足的な開示。株価への影響は限定的とみられる。",
      "analyzed_by": "rules",
      "analyzed_at": "2026-06-30T14:45:54+09:00"
    },
    {
      "id": "a86b9c154f6fddc0",
      "time": "2026-06-30T14:00:00+09:00",
      "code": "2998",
      "company": "Ｇ－クリアル",
      "title": "借入金の期限前返済に関するお知らせ",
      "pdf_url": "https://www.release.tdnet.info140120260630584081.pdf",
      "exchange": "東証",
      "markets": "",
      "source": "scraper",
      "category": "その他開示",
      "score": 35,
      "impact": "low",
      "direction": "unknown",
      "urgent": false,
      "confidence": 40,
      "is_correction": false,
      "tags": [],
      "reasons": [
        "その他開示"
      ],
      "summary": "定例・補足的な開示。株価への影響は限定的とみられる。",
      "analyzed_by": "rules",
      "analyzed_at": "2026-06-30T14:43:21+09:00"
    },
    {
      "id": "ba0233ec7dd2b578",
      "time": "2026-06-30T14:00:00+09:00",
      "code": "322A",
      "company": "Ｐ－ヒメジ理化",
      "title": "代表取締役の異動に関するお知らせ",
      "pdf_url": "https://www.release.tdnet.info140120260630584051.pdf",
      "exchange": "東証",
      "markets": "",
      "source": "scraper",
      "category": "その他開示",
      "score": 35,
      "impact": "low",
      "direction": "unknown",
      "urgent": false,
      "confidence": 40,
      "is_correction": false,
      "tags": [],
      "reasons": [
        "その他開示"
      ],
      "summary": "定例・補足的な開示。株価への影響は限定的とみられる。",
      "analyzed_by": "rules",
      "analyzed_at": "2026-06-30T14:43:21+09:00"
    },
    {
      "id": "a982b74685c680a3",
      "time": "2026-06-30T14:00:00+09:00",
      "code": "5644",
      "company": "メタルアート",
      "title": "非上場の親会社等の決算情報に関するお知らせ",
      "pdf_url": "https://www.release.tdnet.info140120260630584424.pdf",
      "exchange": "東証",
      "markets": "",
      "source": "scraper",
      "category": "その他開示",
      "score": 35,
      "impact": "low",
      "direction": "unknown",
      "urgent": false,
      "confidence": 40,
      "is_correction": false,
      "tags": [],
      "reasons": [
        "その他開示"
      ],
      "summary": "定例・補足的な開示。株価への影響は限定的とみられる。",
      "analyzed_by": "rules",
      "analyzed_at": "2026-06-30T14:43:21+09:00"
    },
    {
      "id": "1262612",
      "time": "2026-06-30T13:20:00+09:00",
      "code": "6625",
      "company": "ＪＡＬＣＯ　ＨＤ",
      "title": "賃貸用不動産の保有目的の変更に関するお知らせ",
      "pdf_url": "https://webapi.yanoshin.jp/rd.php?https://www.release.tdnet.info/inbs/140120260630584589.pdf",
      "exchange": "東証",
      "markets": "",
      "source": "yanoshin",
      "category": "その他開示",
      "score": 35,
      "impact": "low",
      "direction": "unknown",
      "urgent": false,
      "confidence": 40,
      "is_correction": false,
      "tags": [],
      "reasons": [
        "その他開示"
      ],
      "summary": "定例・補足的な開示。株価への影響は限定的とみられる。",
      "analyzed_by": "rules",
      "analyzed_at": "2026-06-30T14:45:54+09:00"
    },
    {
      "id": "1262613",
      "time": "2026-06-30T13:20:00+09:00",
      "code": "6625",
      "company": "ＪＡＬＣＯ　ＨＤ",
      "title": "第13回無担保普通社債の発行及び系統用蓄電池事業に係る匿名組合出資持分の取得に関するお知らせ",
      "pdf_url": "https://webapi.yanoshin.jp/rd.php?https://www.release.tdnet.info/inbs/140120260630584593.pdf",
      "exchange": "東証",
      "markets": "",
      "source": "yanoshin",
      "category": "資金調達",
      "score": 53,
      "impact": "medium",
      "direction": "positive",
      "urgent": false,
      "confidence": 70,
      "is_correction": false,
      "tags": [],
      "reasons": [
        "社債の発行"
      ],
      "summary": "社債発行・借入等の資金調達。財務面の動き。",
      "analyzed_by": "rules",
      "analyzed_at": "2026-06-30T14:45:54+09:00"
    },
    {
      "id": "cf2910f13ac27fe1",
      "time": "2026-06-30T13:20:00+09:00",
      "code": "6625",
      "company": "ＪＡＬＣＯ　ＨＤ",
      "title": "賃貸用不動産の保有目的の変更に関するお知らせ",
      "pdf_url": "https://www.release.tdnet.info140120260630584589.pdf",
      "exchange": "東証",
      "markets": "",
      "source": "scraper",
      "category": "その他開示",
      "score": 35,
      "impact": "low",
      "direction": "unknown",
      "urgent": false,
      "confidence": 40,
      "is_correction": false,
      "tags": [],
      "reasons": [
        "その他開示"
      ],
      "summary": "定例・補足的な開示。株価への影響は限定的とみられる。",
      "analyzed_by": "rules",
      "analyzed_at": "2026-06-30T14:43:21+09:00"
    },
    {
      "id": "a98a596b6bbf10ec",
      "time": "2026-06-30T13:20:00+09:00",
      "code": "6625",
      "company": "ＪＡＬＣＯ　ＨＤ",
      "title": "第13回無担保普通社債の発行及び系統用蓄電池事業に係る匿名組合出資持分の取得に関するお知らせ",
      "pdf_url": "https://www.release.tdnet.info140120260630584593.pdf",
      "exchange": "東証",
      "markets": "",
      "source": "scraper",
      "category": "資金調達",
      "score": 53,
      "impact": "medium",
      "direction": "positive",
      "urgent": false,
      "confidence": 70,
      "is_correction": false,
      "tags": [],
      "reasons": [
        "社債の発行"
      ],
      "summary": "社債発行・借入等の資金調達。財務面の動き。",
      "analyzed_by": "rules",
      "analyzed_at": "2026-06-30T14:43:21+09:00"
    },
    {
      "id": "183fa0bf211b7e0d",
      "time": "2026-06-30T13:00:00+09:00",
      "code": "2737",
      "company": "トーメンデバ",
      "title": "投資単位の引下げに関する考え方及び方針等について",
      "pdf_url": "https://www.release.tdnet.info140120260630584269.pdf",
      "exchange": "東証",
      "markets": "",
      "source": "scraper",
      "category": "その他開示",
      "score": 35,
      "impact": "low",
      "direction": "unknown",
      "urgent": false,
      "confidence": 40,
      "is_correction": false,
      "tags": [],
      "reasons": [
        "その他開示"
      ],
      "summary": "定例・補足的な開示。株価への影響は限定的とみられる。",
      "analyzed_by": "rules",
      "analyzed_at": "2026-06-30T14:43:21+09:00"
    },
    {
      "id": "0e499e8ad1ed3369",
      "time": "2026-06-30T13:00:00+09:00",
      "code": "3437",
      "company": "特殊電極",
      "title": "海外子会社設立に関するお知らせ",
      "pdf_url": "https://www.release.tdnet.info140120260630583983.pdf",
      "exchange": "東証",
      "markets": "",
      "source": "scraper",
      "category": "その他開示",
      "score": 35,
      "impact": "low",
      "direction": "unknown",
      "urgent": false,
      "confidence": 40,
      "is_correction": false,
      "tags": [],
      "reasons": [
        "その他開示"
      ],
      "summary": "定例・補足的な開示。株価への影響は限定的とみられる。",
      "analyzed_by": "rules",
      "analyzed_at": "2026-06-30T14:43:21+09:00"
    },
    {
      "id": "f84db0e3b927d37f",
      "time": "2026-06-30T13:00:00+09:00",
      "code": "4923",
      "company": "ＣＯＴＡ",
      "title": "2026年３月期有価証券報告書の提出期限延長申請の承認に関するお知らせ",
      "pdf_url": "https://www.release.tdnet.info140120260629582657.pdf",
      "exchange": "東証",
      "markets": "",
      "source": "scraper",
      "category": "その他開示",
      "score": 35,
      "impact": "low",
      "direction": "unknown",
      "urgent": false,
      "confidence": 40,
      "is_correction": false,
      "tags": [],
      "reasons": [
        "その他開示"
      ],
      "summary": "定例・補足的な開示。株価への影響は限定的とみられる。",
      "analyzed_by": "rules",
      "analyzed_at": "2026-06-30T14:43:21+09:00"
    },
    {
      "id": "0d8ebb08051be657",
      "time": "2026-06-30T13:00:00+09:00",
      "code": "6580",
      "company": "Ｇ－ライトアップ",
      "title": "事業計画及び成長可能性に関する事項",
      "pdf_url": "https://www.release.tdnet.info140120260629583723.pdf",
      "exchange": "東証",
      "markets": "",
      "source": "scraper",
      "category": "その他開示",
      "score": 35,
      "impact": "low",
      "direction": "unknown",
      "urgent": false,
      "confidence": 40,
      "is_correction": false,
      "tags": [],
      "reasons": [
        "その他開示"
      ],
      "summary": "定例・補足的な開示。株価への影響は限定的とみられる。",
      "analyzed_by": "rules",
      "analyzed_at": "2026-06-30T14:43:21+09:00"
    },
    {
      "id": "98defecf86d479d8",
      "time": "2026-06-30T13:00:00+09:00",
      "code": "7292",
      "company": "村上開明",
      "title": "投資単位の引下げに関する考え方及び方針等について",
      "pdf_url": "https://www.release.tdnet.info140120260630584015.pdf",
      "exchange": "東証",
      "markets": "",
      "source": "scraper",
      "category": "その他開示",
      "score": 35,
      "impact": "low",
      "direction": "unknown",
      "urgent": false,
      "confidence": 40,
      "is_correction": false,
      "tags": [],
      "reasons": [
        "その他開示"
      ],
      "summary": "定例・補足的な開示。株価への影響は限定的とみられる。",
      "analyzed_by": "rules",
      "analyzed_at": "2026-06-30T14:43:21+09:00"
    },
    {
      "id": "1262615",
      "time": "2026-06-30T13:00:00+09:00",
      "code": "2737",
      "company": "トーメンデバ",
      "title": "投資単位の引下げに関する考え方及び方針等について",
      "pdf_url": "https://webapi.yanoshin.jp/rd.php?https://www.release.tdnet.info/inbs/140120260630584269.pdf",
      "exchange": "東証",
      "markets": "",
      "source": "yanoshin",
      "category": "その他開示",
      "score": 35,
      "impact": "low",
      "direction": "unknown",
      "urgent": false,
      "confidence": 40,
      "is_correction": false,
      "tags": [],
      "reasons": [
        "その他開示"
      ],
      "summary": "定例・補足的な開示。株価への影響は限定的とみられる。",
      "analyzed_by": "rules",
      "analyzed_at": "2026-06-30T14:45:54+09:00"
    },
    {
      "id": "1262616",
      "time": "2026-06-30T13:00:00+09:00",
      "code": "3437",
      "company": "特殊電極",
      "title": "海外子会社設立に関するお知らせ",
      "pdf_url": "https://webapi.yanoshin.jp/rd.php?https://www.release.tdnet.info/inbs/140120260630583983.pdf",
      "exchange": "東証",
      "markets": "",
      "source": "yanoshin",
      "category": "その他開示",
      "score": 35,
      "impact": "low",
      "direction": "unknown",
      "urgent": false,
      "confidence": 40,
      "is_correction": false,
      "tags": [],
      "reasons": [
        "その他開示"
      ],
      "summary": "定例・補足的な開示。株価への影響は限定的とみられる。",
      "analyzed_by": "rules",
      "analyzed_at": "2026-06-30T14:45:54+09:00"
    },
    {
      "id": "1262617",
      "time": "2026-06-30T13:00:00+09:00",
      "code": "4923",
      "company": "ＣＯＴＡ",
      "title": "2026年３月期有価証券報告書の提出期限延長申請の承認に関するお知らせ",
      "pdf_url": "https://webapi.yanoshin.jp/rd.php?https://www.release.tdnet.info/inbs/140120260629582657.pdf",
      "exchange": "東証",
      "markets": "",
      "source": "yanoshin",
      "category": "その他開示",
      "score": 35,
      "impact": "low",
      "direction": "unknown",
      "urgent": false,
      "confidence": 40,
      "is_correction": false,
      "tags": [],
      "reasons": [
        "その他開示"
      ],
      "summary": "定例・補足的な開示。株価への影響は限定的とみられる。",
      "analyzed_by": "rules",
      "analyzed_at": "2026-06-30T14:45:54+09:00"
    },
    {
      "id": "1262619",
      "time": "2026-06-30T13:00:00+09:00",
      "code": "6580",
      "company": "Ｇ－ライトアップ",
      "title": "事業計画及び成長可能性に関する事項",
      "pdf_url": "https://webapi.yanoshin.jp/rd.php?https://www.release.tdnet.info/inbs/140120260629583723.pdf",
      "exchange": "東証",
      "markets": "",
      "source": "yanoshin",
      "category": "その他開示",
      "score": 35,
      "impact": "low",
      "direction": "unknown",
      "urgent": false,
      "confidence": 40,
      "is_correction": false,
      "tags": [],
      "reasons": [
        "その他開示"
      ],
      "summary": "定例・補足的な開示。株価への影響は限定的とみられる。",
      "analyzed_by": "rules",
      "analyzed_at": "2026-06-30T14:45:54+09:00"
    },
    {
      "id": "1262620",
      "time": "2026-06-30T13:00:00+09:00",
      "code": "7292",
      "company": "村上開明",
      "title": "投資単位の引下げに関する考え方及び方針等について",
      "pdf_url": "https://webapi.yanoshin.jp/rd.php?https://www.release.tdnet.info/inbs/140120260630584015.pdf",
      "exchange": "東証",
      "markets": "",
      "source": "yanoshin",
      "category": "その他開示",
      "score": 35,
      "impact": "low",
      "direction": "unknown",
      "urgent": false,
      "confidence": 40,
      "is_correction": false,
      "tags": [],
      "reasons": [
        "その他開示"
      ],
      "summary": "定例・補足的な開示。株価への影響は限定的とみられる。",
      "analyzed_by": "rules",
      "analyzed_at": "2026-06-30T14:45:54+09:00"
    },
    {
      "id": "1262607",
      "time": "2026-06-30T12:30:00+09:00",
      "code": "3856",
      "company": "Ａｂａｌａｎｃｅ",
      "title": "調査委員会の調査報告書受領に関するお知らせ",
      "pdf_url": "https://webapi.yanoshin.jp/rd.php?https://www.release.tdnet.info/inbs/140120260630584388.pdf",
      "exchange": "東証",
      "markets": "",
      "source": "yanoshin",
      "category": "その他開示",
      "score": 35,
      "impact": "low",
      "direction": "unknown",
      "urgent": false,
      "confidence": 40,
      "is_correction": false,
      "tags": [],
      "reasons": [
        "その他開示"
      ],
      "summary": "定例・補足的な開示。株価への影響は限定的とみられる。",
      "analyzed_by": "rules",
      "analyzed_at": "2026-06-30T14:45:54+09:00"
    },
    {
      "id": "1262608",
      "time": "2026-06-30T12:30:00+09:00",
      "code": "3856",
      "company": "Ａｂａｌａｎｃｅ",
      "title": "第27期有価証券報告書提出期限の延長に係る承認申請書提出のお知らせ",
      "pdf_url": "https://webapi.yanoshin.jp/rd.php?https://www.release.tdnet.info/inbs/140120260630584399.pdf",
      "exchange": "東証",
      "markets": "",
      "source": "yanoshin",
      "category": "その他開示",
      "score": 35,
      "impact": "low",
      "direction": "unknown",
      "urgent": false,
      "confidence": 40,
      "is_correction": false,
      "tags": [],
      "reasons": [
        "その他開示"
      ],
      "summary": "定例・補足的な開示。株価への影響は限定的とみられる。",
      "analyzed_by": "rules",
      "analyzed_at": "2026-06-30T14:45:54+09:00"
    },
    {
      "id": "3283e70a0958c072",
      "time": "2026-06-30T12:30:00+09:00",
      "code": "3856",
      "company": "Ａｂａｌａｎｃｅ",
      "title": "調査委員会の調査報告書受領に関するお知らせ",
      "pdf_url": "https://www.release.tdnet.info140120260630584388.pdf",
      "exchange": "東証",
      "markets": "",
      "source": "scraper",
      "category": "その他開示",
      "score": 35,
      "impact": "low",
      "direction": "unknown",
      "urgent": false,
      "confidence": 40,
      "is_correction": false,
      "tags": [],
      "reasons": [
        "その他開示"
      ],
      "summary": "定例・補足的な開示。株価への影響は限定的とみられる。",
      "analyzed_by": "rules",
      "analyzed_at": "2026-06-30T14:43:21+09:00"
    },
    {
      "id": "57c4c5d4c109a495",
      "time": "2026-06-30T12:30:00+09:00",
      "code": "3856",
      "company": "Ａｂａｌａｎｃｅ",
      "title": "第27期有価証券報告書提出期限の延長に係る承認申請書提出のお知らせ",
      "pdf_url": "https://www.release.tdnet.info140120260630584399.pdf",
      "exchange": "東証",
      "markets": "",
      "source": "scraper",
      "category": "その他開示",
      "score": 35,
      "impact": "low",
      "direction": "unknown",
      "urgent": false,
      "confidence": 40,
      "is_correction": false,
      "tags": [],
      "reasons": [
        "その他開示"
      ],
      "summary": "定例・補足的な開示。株価への影響は限定的とみられる。",
      "analyzed_by": "rules",
      "analyzed_at": "2026-06-30T14:43:21+09:00"
    },
    {
      "id": "1262610",
      "time": "2026-06-30T12:15:00+09:00",
      "code": "587A",
      "company": "Ｅ－インベスコＱＱＱ",
      "title": "インベスコQQQトラスト シリーズ1 に関する日々の開示事項",
      "pdf_url": "https://webapi.yanoshin.jp/rd.php?https://www.release.tdnet.info/inbs/140120260630584390.pdf",
      "exchange": "東証",
      "markets": "",
      "source": "yanoshin",
      "category": "その他開示",
      "score": 35,
      "impact": "low",
      "direction": "unknown",
      "urgent": false,
      "confidence": 40,
      "is_correction": false,
      "tags": [],
      "reasons": [
        "その他開示"
      ],
      "summary": "定例・補足的な開示。株価への影響は限定的とみられる。",
      "analyzed_by": "rules",
      "analyzed_at": "2026-06-30T14:45:54+09:00"
    },
    {
      "id": "082ea5845ab19850",
      "time": "2026-06-30T12:15:00+09:00",
      "code": "587A",
      "company": "Ｅ－インベスコＱＱＱ",
      "title": "インベスコQQQトラスト シリーズ1 に関する日々の開示事項",
      "pdf_url": "https://www.release.tdnet.info140120260630584390.pdf",
      "exchange": "東証",
      "markets": "",
      "source": "scraper",
      "category": "その他開示",
      "score": 35,
      "impact": "low",
      "direction": "unknown",
      "urgent": false,
      "confidence": 40,
      "is_correction": false,
      "tags": [],
      "reasons": [
        "その他開示"
      ],
      "summary": "定例・補足的な開示。株価への影響は限定的とみられる。",
      "analyzed_by": "rules",
      "analyzed_at": "2026-06-30T14:43:21+09:00"
    },
    {
      "id": "1262600",
      "time": "2026-06-30T12:00:00+09:00",
      "code": "1326",
      "company": "Ｅ－ワールド",
      "title": "SPDRゴールド・シェアに関する日々の開示事項",
      "pdf_url": "https://webapi.yanoshin.jp/rd.php?https://www.release.tdnet.info/inbs/140120260630584318.pdf",
      "exchange": "東証",
      "markets": "",
      "source": "yanoshin",
      "category": "その他開示",
      "score": 35,
      "impact": "low",
      "direction": "unknown",
      "urgent": false,
      "confidence": 40,
      "is_correction": false,
      "tags": [],
      "reasons": [
        "その他開示"
      ],
      "summary": "定例・補足的な開示。株価への影響は限定的とみられる。",
      "analyzed_by": "rules",
      "analyzed_at": "2026-06-30T14:45:54+09:00"
    },
    {
      "id": "1262602",
      "time": "2026-06-30T12:00:00+09:00",
      "code": "1780",
      "company": "ヤマウラ",
      "title": "自己株式立会外買付取引（ToSTNeT-3）による自己株式の取得結果及び自己株式の消却に関するお知らせ",
      "pdf_url": "https://webapi.yanoshin.jp/rd.php?https://www.release.tdnet.info/inbs/140120260630584366.pdf",
      "exchange": "東証",
      "markets": "",
      "source": "yanoshin",
      "category": "自社株買い",
      "score": 81,
      "impact": "high",
      "direction": "positive",
      "urgent": true,
      "confidence": 88,
      "is_correction": false,
      "tags": [
        "自己株式の取得",
        "自己株式の消却"
      ],
      "reasons": [
        "自己株式の取得"
      ],
      "summary": "自己株式取得は需給改善・株主還元でポジティブ。",
      "analyzed_by": "rules",
      "analyzed_at": "2026-06-30T14:45:54+09:00"
    },
    {
      "id": "1262603",
      "time": "2026-06-30T12:00:00+09:00",
      "code": "311A",
      "company": "Ｐ－ＮＰＴ",
      "title": "臨時株主総会の決議結果及び上場廃止申請に関するお知らせ",
      "pdf_url": "https://webapi.yanoshin.jp/rd.php?https://www.release.tdnet.info/inbs/140120260625579659.pdf",
      "exchange": "東証",
      "markets": "",
      "source": "yanoshin",
      "category": "上場廃止・整理",
      "score": 75,
      "impact": "high",
      "direction": "negative",
      "urgent": false,
      "confidence": 76,
      "is_correction": true,
      "tags": [
        "上場廃止"
      ],
      "reasons": [
        "上場廃止",
        "減衰:株主総会"
      ],
      "summary": "上場廃止・監理/整理。重大な下落リスク。",
      "analyzed_by": "rules",
      "analyzed_at": "2026-06-30T14:45:54+09:00"
    },
    {
      "id": "1262604",
      "time": "2026-06-30T12:00:00+09:00",
      "code": "9165",
      "company": "Ｇ－クオルテック",
      "title": "経済産業省「成長型中小企業等研究開発支援事業（Go-Tech事業）」採択に関するお知らせ",
      "pdf_url": "https://webapi.yanoshin.jp/rd.php?https://www.release.tdnet.info/inbs/140120260629583099.pdf",
      "exchange": "東証",
      "markets": "",
      "source": "yanoshin",
      "category": "その他開示",
      "score": 35,
      "impact": "low",
      "direction": "unknown",
      "urgent": false,
      "confidence": 40,
      "is_correction": false,
      "tags": [],
      "reasons": [
        "その他開示"
      ],
      "summary": "定例・補足的な開示。株価への影響は限定的とみられる。",
      "analyzed_by": "rules",
      "analyzed_at": "2026-06-30T14:45:54+09:00"
    },
    {
      "id": "bb198e567a2d8f04",
      "time": "2026-06-30T12:00:00+09:00",
      "code": "1326",
      "company": "Ｅ－ワールド",
      "title": "SPDRゴールド・シェアに関する日々の開示事項",
      "pdf_url": "https://www.release.tdnet.info140120260630584318.pdf",
      "exchange": "東証",
      "markets": "",
      "source": "scraper",
      "category": "その他開示",
      "score": 35,
      "impact": "low",
      "direction": "unknown",
      "urgent": false,
      "confidence": 40,
      "is_correction": false,
      "tags": [],
      "reasons": [
        "その他開示"
      ],
      "summary": "定例・補足的な開示。株価への影響は限定的とみられる。",
      "analyzed_by": "rules",
      "analyzed_at": "2026-06-30T14:43:21+09:00"
    },
    {
      "id": "cf4810c5209301aa",
      "time": "2026-06-30T12:00:00+09:00",
      "code": "1780",
      "company": "ヤマウラ",
      "title": "自己株式立会外買付取引（ToSTNeT-3）による自己株式の取得結果及び自己株式の消却に関するお知らせ",
      "pdf_url": "https://www.release.tdnet.info140120260630584366.pdf",
      "exchange": "東証",
      "markets": "",
      "source": "scraper",
      "category": "自社株買い",
      "score": 81,
      "impact": "high",
      "direction": "positive",
      "urgent": true,
      "confidence": 88,
      "is_correction": false,
      "tags": [
        "自己株式の取得",
        "自己株式の消却"
      ],
      "reasons": [
        "自己株式の取得"
      ],
      "summary": "自己株式取得は需給改善・株主還元でポジティブ。",
      "analyzed_by": "rules",
      "analyzed_at": "2026-06-30T14:43:21+09:00"
    },
    {
      "id": "4e80f35496db78ef",
      "time": "2026-06-30T12:00:00+09:00",
      "code": "311A",
      "company": "Ｐ－ＮＰＴ",
      "title": "臨時株主総会の決議結果及び上場廃止申請に関するお知らせ",
      "pdf_url": "https://www.release.tdnet.info140120260625579659.pdf",
      "exchange": "東証",
      "markets": "",
      "source": "scraper",
      "category": "上場廃止・整理",
      "score": 75,
      "impact": "high",
      "direction": "negative",
      "urgent": false,
      "confidence": 76,
      "is_correction": true,
      "tags": [
        "上場廃止"
      ],
      "reasons": [
        "上場廃止",
        "減衰:株主総会"
      ],
      "summary": "上場廃止・監理/整理。重大な下落リスク。",
      "analyzed_by": "rules",
      "analyzed_at": "2026-06-30T14:43:21+09:00"
    },
    {
      "id": "953708401a522c88",
      "time": "2026-06-30T12:00:00+09:00",
      "code": "9165",
      "company": "Ｇ－クオルテック",
      "title": "経済産業省「成長型中小企業等研究開発支援事業（Go-Tech事業）」採択に関するお知らせ",
      "pdf_url": "https://www.release.tdnet.info140120260629583099.pdf",
      "exchange": "東証",
      "markets": "",
      "source": "scraper",
      "category": "その他開示",
      "score": 35,
      "impact": "low",
      "direction": "unknown",
      "urgent": false,
      "confidence": 40,
      "is_correction": false,
      "tags": [],
      "reasons": [
        "その他開示"
      ],
      "summary": "定例・補足的な開示。株価への影響は限定的とみられる。",
      "analyzed_by": "rules",
      "analyzed_at": "2026-06-30T14:43:21+09:00"
    },
    {
      "id": "1262605",
      "time": "2026-06-30T11:55:00+09:00",
      "code": "1349",
      "company": "Ｅ－ＳＳＧＡ－ＳＩＮ",
      "title": "アジア国債・公債ＥＴＦ（正式名称：ＡＢＦ汎アジア債券インデックス・ファンド）に関する日々の開示事項",
      "pdf_url": "https://webapi.yanoshin.jp/rd.php?https://www.release.tdnet.info/inbs/140120260630584315.pdf",
      "exchange": "東証",
      "markets": "",
      "source": "yanoshin",
      "category": "その他開示",
      "score": 35,
      "impact": "low",
      "direction": "unknown",
      "urgent": false,
      "confidence": 40,
      "is_correction": false,
      "tags": [],
      "reasons": [
        "その他開示"
      ],
      "summary": "定例・補足的な開示。株価への影響は限定的とみられる。",
      "analyzed_by": "rules",
      "analyzed_at": "2026-06-30T14:45:54+09:00"
    },
    {
      "id": "7b20f618fdf08e9c",
      "time": "2026-06-30T11:55:00+09:00",
      "code": "1349",
      "company": "Ｅ－ＳＳＧＡ－ＳＩＮ",
      "title": "アジア国債・公債ＥＴＦ（正式名称：ＡＢＦ汎アジア債券インデックス・ファンド）に関する日々の開示事項",
      "pdf_url": "https://www.release.tdnet.info140120260630584315.pdf",
      "exchange": "東証",
      "markets": "",
      "source": "scraper",
      "category": "その他開示",
      "score": 35,
      "impact": "low",
      "direction": "unknown",
      "urgent": false,
      "confidence": 40,
      "is_correction": false,
      "tags": [],
      "reasons": [
        "その他開示"
      ],
      "summary": "定例・補足的な開示。株価への影響は限定的とみられる。",
      "analyzed_by": "rules",
      "analyzed_at": "2026-06-30T14:43:21+09:00"
    },
    {
      "id": "1262606",
      "time": "2026-06-30T11:50:00+09:00",
      "code": "1557",
      "company": "Ｅ－ＳＳＧＡＴＣ",
      "title": "State Street SPDR S&amp;P500 ETFに関する日々の開示事項",
      "pdf_url": "https://webapi.yanoshin.jp/rd.php?https://www.release.tdnet.info/inbs/140120260630584329.pdf",
      "exchange": "東証",
      "markets": "",
      "source": "yanoshin",
      "category": "その他開示",
      "score": 35,
      "impact": "low",
      "direction": "unknown",
      "urgent": false,
      "confidence": 40,
      "is_correction": false,
      "tags": [],
      "reasons": [
        "その他開示"
      ],
      "summary": "定例・補足的な開示。株価への影響は限定的とみられる。",
      "analyzed_by": "rules",
      "analyzed_at": "2026-06-30T14:45:54+09:00"
    },
    {
      "id": "173e73e5bf7d1d59",
      "time": "2026-06-30T11:50:00+09:00",
      "code": "1557",
      "company": "Ｅ－ＳＳＧＡＴＣ",
      "title": "State Street SPDR S&P500 ETFに関する日々の開示事項",
      "pdf_url": "https://www.release.tdnet.info140120260630584329.pdf",
      "exchange": "東証",
      "markets": "",
      "source": "scraper",
      "category": "その他開示",
      "score": 35,
      "impact": "low",
      "direction": "unknown",
      "urgent": false,
      "confidence": 40,
      "is_correction": false,
      "tags": [],
      "reasons": [
        "その他開示"
      ],
      "summary": "定例・補足的な開示。株価への影響は限定的とみられる。",
      "analyzed_by": "rules",
      "analyzed_at": "2026-06-30T14:43:21+09:00"
    },
    {
      "id": "1262595",
      "time": "2026-06-30T11:30:00+09:00",
      "code": "1429",
      "company": "日本アクア",
      "title": "非上場の親会社等の決算情報に関するお知らせ",
      "pdf_url": "https://webapi.yanoshin.jp/rd.php?https://www.release.tdnet.info/inbs/140120260616571872.pdf",
      "exchange": "東証",
      "markets": "",
      "source": "yanoshin",
      "category": "その他開示",
      "score": 35,
      "impact": "low",
      "direction": "unknown",
      "urgent": false,
      "confidence": 40,
      "is_correction": false,
      "tags": [],
      "reasons": [
        "その他開示"
      ],
      "summary": "定例・補足的な開示。株価への影響は限定的とみられる。",
      "analyzed_by": "rules",
      "analyzed_at": "2026-06-30T14:45:54+09:00"
    },
    {
      "id": "1262596",
      "time": "2026-06-30T11:30:00+09:00",
      "code": "2070",
      "company": "Ｎ－三菱ＵＦＪ証ＨＤ",
      "title": "上場ETN（発行者：三菱UFJ証券ホールディングス株式会社）に関する日々の開示事項",
      "pdf_url": "https://webapi.yanoshin.jp/rd.php?https://www.release.tdnet.info/inbs/140120260630584229.pdf",
      "exchange": "東証",
      "markets": "",
      "source": "yanoshin",
      "category": "その他開示",
      "score": 35,
      "impact": "low",
      "direction": "unknown",
      "urgent": false,
      "confidence": 40,
      "is_correction": false,
      "tags": [],
      "reasons": [
        "その他開示"
      ],
      "summary": "定例・補足的な開示。株価への影響は限定的とみられる。",
      "analyzed_by": "rules",
      "analyzed_at": "2026-06-30T14:45:54+09:00"
    },
    {
      "id": "1262597",
      "time": "2026-06-30T11:30:00+09:00",
      "code": "5031",
      "company": "Ｇ－モイ",
      "title": "（開示事項の経過）第三者割当増資による新株式の発行に係る払込完了に関するお知らせ",
      "pdf_url": "https://webapi.yanoshin.jp/rd.php?https://www.release.tdnet.info/inbs/140120260630584190.pdf",
      "exchange": "東証",
      "markets": "",
      "source": "yanoshin",
      "category": "増資・希薄化",
      "score": 47,
      "impact": "medium",
      "direction": "negative",
      "urgent": false,
      "confidence": 76,
      "is_correction": true,
      "tags": [
        "第三者割当",
        "増資"
      ],
      "reasons": [
        "第三者割当",
        "減衰:払込完了"
      ],
      "summary": "新株発行・希薄化は短期的に売られやすい。",
      "analyzed_by": "rules",
      "analyzed_at": "2026-06-30T14:45:54+09:00"
    },
    {
      "id": "d3329bc92d4053c5",
      "time": "2026-06-30T11:30:00+09:00",
      "code": "1429",
      "company": "日本アクア",
      "title": "非上場の親会社等の決算情報に関するお知らせ",
      "pdf_url": "https://www.release.tdnet.info140120260616571872.pdf",
      "exchange": "東証",
      "markets": "",
      "source": "scraper",
      "category": "その他開示",
      "score": 35,
      "impact": "low",
      "direction": "unknown",
      "urgent": false,
      "confidence": 40,
      "is_correction": false,
      "tags": [],
      "reasons": [
        "その他開示"
      ],
      "summary": "定例・補足的な開示。株価への影響は限定的とみられる。",
      "analyzed_by": "rules",
      "analyzed_at": "2026-06-30T14:43:21+09:00"
    },
    {
      "id": "b3427010b9055132",
      "time": "2026-06-30T11:30:00+09:00",
      "code": "2070",
      "company": "Ｎ－三菱ＵＦＪ証ＨＤ",
      "title": "上場ETN（発行者：三菱UFJ証券ホールディングス株式会社）に関する日々の開示事項",
      "pdf_url": "https://www.release.tdnet.info140120260630584229.pdf",
      "exchange": "東証",
      "markets": "",
      "source": "scraper",
      "category": "その他開示",
      "score": 35,
      "impact": "low",
      "direction": "unknown",
      "urgent": false,
      "confidence": 40,
      "is_correction": false,
      "tags": [],
      "reasons": [
        "その他開示"
      ],
      "summary": "定例・補足的な開示。株価への影響は限定的とみられる。",
      "analyzed_by": "rules",
      "analyzed_at": "2026-06-30T14:43:21+09:00"
    },
    {
      "id": "c15ceb58bbf02934",
      "time": "2026-06-30T11:30:00+09:00",
      "code": "5031",
      "company": "Ｇ－モイ",
      "title": "（開示事項の経過）第三者割当増資による新株式の発行に係る払込完了に関するお知らせ",
      "pdf_url": "https://www.release.tdnet.info140120260630584190.pdf",
      "exchange": "東証",
      "markets": "",
      "source": "scraper",
      "category": "増資・希薄化",
      "score": 47,
      "impact": "medium",
      "direction": "negative",
      "urgent": false,
      "confidence": 76,
      "is_correction": true,
      "tags": [
        "第三者割当",
        "増資"
      ],
      "reasons": [
        "第三者割当",
        "減衰:払込完了"
      ],
      "summary": "新株発行・希薄化は短期的に売られやすい。",
      "analyzed_by": "rules",
      "analyzed_at": "2026-06-30T14:43:21+09:00"
    },
    {
      "id": "1262589",
      "time": "2026-06-30T11:00:00+09:00",
      "code": "1847",
      "company": "イチケン",
      "title": "親会社等の決算に関するお知らせ",
      "pdf_url": "https://webapi.yanoshin.jp/rd.php?https://www.release.tdnet.info/inbs/140120260629583650.pdf",
      "exchange": "東証",
      "markets": "",
      "source": "yanoshin",
      "category": "その他開示",
      "score": 35,
      "impact": "low",
      "direction": "unknown",
      "urgent": false,
      "confidence": 40,
      "is_correction": false,
      "tags": [],
      "reasons": [
        "その他開示"
      ],
      "summary": "定例・補足的な開示。株価への影響は限定的とみられる。",
      "analyzed_by": "rules",
      "analyzed_at": "2026-06-30T14:45:54+09:00"
    },
    {
      "id": "1262592",
      "time": "2026-06-30T11:00:00+09:00",
      "code": "8011",
      "company": "三陽商",
      "title": "2027年２月期 第１四半期決算短信〔日本基準〕（連結）",
      "pdf_url": "https://webapi.yanoshin.jp/rd.php?https://www.release.tdnet.info/inbs/140120260630584087.pdf",
      "exchange": "東証",
      "markets": "",
      "source": "yanoshin",
      "category": "決算",
      "score": 53,
      "impact": "medium",
      "direction": "neutral",
      "urgent": false,
      "confidence": 65,
      "is_correction": false,
      "tags": [],
      "reasons": [
        "決算短信"
      ],
      "summary": "決算発表。コンセンサス比で方向が決まる(本文要確認)。",
      "analyzed_by": "rules",
      "analyzed_at": "2026-06-30T14:45:54+09:00",
      "earnings": {
        "period": "2027年２月期  第１四半期",
        "figures": [
          {
            "label": "純利益",
            "value": "１百万円"
          }
        ],
        "source": "regex"
      }
    },
    {
      "id": "1262593",
      "time": "2026-06-30T11:00:00+09:00",
      "code": "8011",
      "company": "三陽商",
      "title": "配当方針の変更及び配当予想の修正（増配）に関するお知らせ",
      "pdf_url": "https://webapi.yanoshin.jp/rd.php?https://www.release.tdnet.info/inbs/140120260626581603.pdf",
      "exchange": "東証",
      "markets": "",
      "source": "yanoshin",
      "category": "配当",
      "score": 83,
      "impact": "high",
      "direction": "positive",
      "urgent": true,
      "confidence": 88,
      "is_correction": false,
      "tags": [
        "増配"
      ],
      "reasons": [
        "配当予想の修正"
      ],
      "summary": "増配・株主還元の強化でポジティブ。",
      "analyzed_by": "rules",
      "analyzed_at": "2026-06-30T14:45:54+09:00"
    },
    {
      "id": "8561379dc06d9b8b",
      "time": "2026-06-30T11:00:00+09:00",
      "code": "1847",
      "company": "イチケン",
      "title": "親会社等の決算に関するお知らせ",
      "pdf_url": "https://www.release.tdnet.info140120260629583650.pdf",
      "exchange": "東証",
      "markets": "",
      "source": "scraper",
      "category": "その他開示",
      "score": 35,
      "impact": "low",
      "direction": "unknown",
      "urgent": false,
      "confidence": 40,
      "is_correction": false,
      "tags": [],
      "reasons": [
        "その他開示"
      ],
      "summary": "定例・補足的な開示。株価への影響は限定的とみられる。",
      "analyzed_by": "rules",
      "analyzed_at": "2026-06-30T14:43:21+09:00"
    },
    {
      "id": "3a520df83dc30213",
      "time": "2026-06-30T11:00:00+09:00",
      "code": "8011",
      "company": "三陽商",
      "title": "2027年２月期 第１四半期決算短信〔日本基準〕（連結）",
      "pdf_url": "https://www.release.tdnet.info140120260630584087.pdf",
      "exchange": "東証",
      "markets": "",
      "source": "scraper",
      "category": "決算",
      "score": 53,
      "impact": "medium",
      "direction": "neutral",
      "urgent": false,
      "confidence": 65,
      "is_correction": false,
      "tags": [],
      "reasons": [
        "決算短信"
      ],
      "summary": "決算発表。コンセンサス比で方向が決まる(本文要確認)。",
      "analyzed_by": "rules",
      "analyzed_at": "2026-06-30T14:43:21+09:00"
    },
    {
      "id": "25feecdad39c3356",
      "time": "2026-06-30T11:00:00+09:00",
      "code": "8011",
      "company": "三陽商",
      "title": "配当方針の変更及び配当予想の修正（増配）に関するお知らせ",
      "pdf_url": "https://www.release.tdnet.info140120260626581603.pdf",
      "exchange": "東証",
      "markets": "",
      "source": "scraper",
      "category": "配当",
      "score": 83,
      "impact": "high",
      "direction": "positive",
      "urgent": true,
      "confidence": 88,
      "is_correction": false,
      "tags": [
        "増配"
      ],
      "reasons": [
        "配当予想の修正"
      ],
      "summary": "増配・株主還元の強化でポジティブ。",
      "analyzed_by": "rules",
      "analyzed_at": "2026-06-30T14:43:21+09:00"
    },
    {
      "id": "1262581",
      "time": "2026-06-30T10:40:00+09:00",
      "code": "2241",
      "company": "ＭＸＳダウ",
      "title": "ＭＡＸＩＳ ＮＹダウ上場投信 決算短信（2026年5月期）",
      "pdf_url": "https://webapi.yanoshin.jp/rd.php?https://www.release.tdnet.info/inbs/140120260630584151.pdf",
      "exchange": "東証",
      "markets": "",
      "source": "yanoshin",
      "category": "決算",
      "score": 53,
      "impact": "medium",
      "direction": "neutral",
      "urgent": false,
      "confidence": 65,
      "is_correction": false,
      "tags": [],
      "reasons": [
        "決算短信"
      ],
      "summary": "決算発表。コンセンサス比で方向が決まる(本文要確認)。",
      "analyzed_by": "rules",
      "analyzed_at": "2026-06-30T14:45:54+09:00",
      "earnings": {
        "period": null,
        "figures": [
          {
            "label": "売上高",
            "value": "28,999百万円",
            "yoy": "+66%"
          }
        ],
        "source": "regex"
      }
    },
    {
      "id": "1262582",
      "time": "2026-06-30T10:40:00+09:00",
      "code": "2242",
      "company": "ＭＸＳダウヘ有",
      "title": "ＭＡＸＩＳ ＮＹダウ上場投信（為替ヘッジあり） 決算短信（2026年5月期）",
      "pdf_url": "https://webapi.yanoshin.jp/rd.php?https://www.release.tdnet.info/inbs/140120260630584181.pdf",
      "exchange": "東証",
      "markets": "",
      "source": "yanoshin",
      "category": "決算",
      "score": 53,
      "impact": "medium",
      "direction": "neutral",
      "urgent": false,
      "confidence": 65,
      "is_correction": false,
      "tags": [],
      "reasons": [
        "決算短信"
      ],
      "summary": "決算発表。コンセンサス比で方向が決まる(本文要確認)。",
      "analyzed_by": "rules",
      "analyzed_at": "2026-06-30T14:45:54+09:00",
      "earnings": {
        "period": null,
        "figures": [
          {
            "label": "売上高",
            "value": "18,340百万円",
            "yoy": "+30%"
          }
        ],
        "source": "regex"
      }
    },
    {
      "id": "73c493ae35f05a30",
      "time": "2026-06-30T10:40:00+09:00",
      "code": "2241",
      "company": "ＭＸＳダウ",
      "title": "ＭＡＸＩＳ ＮＹダウ上場投信 決算短信（2026年5月期）",
      "pdf_url": "https://www.release.tdnet.info140120260630584151.pdf",
      "exchange": "東証",
      "markets": "",
      "source": "scraper",
      "category": "決算",
      "score": 53,
      "impact": "medium",
      "direction": "neutral",
      "urgent": false,
      "confidence": 65,
      "is_correction": false,
      "tags": [],
      "reasons": [
        "決算短信"
      ],
      "summary": "決算発表。コンセンサス比で方向が決まる(本文要確認)。",
      "analyzed_by": "rules",
      "analyzed_at": "2026-06-30T14:43:21+09:00"
    },
    {
      "id": "7abd6ece1e8ced7a",
      "time": "2026-06-30T10:40:00+09:00",
      "code": "2242",
      "company": "ＭＸＳダウヘ有",
      "title": "ＭＡＸＩＳ ＮＹダウ上場投信（為替ヘッジあり） 決算短信（2026年5月期）",
      "pdf_url": "https://www.release.tdnet.info140120260630584181.pdf",
      "exchange": "東証",
      "markets": "",
      "source": "scraper",
      "category": "決算",
      "score": 53,
      "impact": "medium",
      "direction": "neutral",
      "urgent": false,
      "confidence": 65,
      "is_correction": false,
      "tags": [],
      "reasons": [
        "決算短信"
      ],
      "summary": "決算発表。コンセンサス比で方向が決まる(本文要確認)。",
      "analyzed_by": "rules",
      "analyzed_at": "2026-06-30T14:43:21+09:00"
    },
    {
      "id": "1262584",
      "time": "2026-06-30T10:30:00+09:00",
      "code": "6850",
      "company": "チノー",
      "title": "資本コストや株価を意識した経営の実現に向けた対応について（アップデート）",
      "pdf_url": "https://webapi.yanoshin.jp/rd.php?https://www.release.tdnet.info/inbs/140120260625580838.pdf",
      "exchange": "東証",
      "markets": "",
      "source": "yanoshin",
      "category": "その他開示",
      "score": 35,
      "impact": "low",
      "direction": "unknown",
      "urgent": false,
      "confidence": 40,
      "is_correction": false,
      "tags": [],
      "reasons": [
        "その他開示"
      ],
      "summary": "定例・補足的な開示。株価への影響は限定的とみられる。",
      "analyzed_by": "rules",
      "analyzed_at": "2026-06-30T14:45:54+09:00"
    },
    {
      "id": "d44d1af5c845eb43",
      "time": "2026-06-30T10:30:00+09:00",
      "code": "6850",
      "company": "チノー",
      "title": "資本コストや株価を意識した経営の実現に向けた対応について（アップデート）",
      "pdf_url": "https://www.release.tdnet.info140120260625580838.pdf",
      "exchange": "東証",
      "markets": "",
      "source": "scraper",
      "category": "その他開示",
      "score": 35,
      "impact": "low",
      "direction": "unknown",
      "urgent": false,
      "confidence": 40,
      "is_correction": false,
      "tags": [],
      "reasons": [
        "その他開示"
      ],
      "summary": "定例・補足的な開示。株価への影響は限定的とみられる。",
      "analyzed_by": "rules",
      "analyzed_at": "2026-06-30T14:43:21+09:00"
    },
    {
      "id": "1262575",
      "time": "2026-06-30T10:10:00+09:00",
      "code": "585A",
      "company": "Ｅ－ＪＡＭＰＦＭ",
      "title": "上場ETF（管理会社：JAMPファンド・マネジメント）に関する日々の開示事項",
      "pdf_url": "https://webapi.yanoshin.jp/rd.php?https://www.release.tdnet.info/inbs/140120260630583959.pdf",
      "exchange": "東証",
      "markets": "",
      "source": "yanoshin",
      "category": "その他開示",
      "score": 35,
      "impact": "low",
      "direction": "unknown",
      "urgent": false,
      "confidence": 40,
      "is_correction": false,
      "tags": [],
      "reasons": [
        "その他開示"
      ],
      "summary": "定例・補足的な開示。株価への影響は限定的とみられる。",
      "analyzed_by": "rules",
      "analyzed_at": "2026-06-30T14:45:54+09:00"
    },
    {
      "id": "5132d93bc9ed03d6",
      "time": "2026-06-30T10:10:00+09:00",
      "code": "585A",
      "company": "Ｅ－ＪＡＭＰＦＭ",
      "title": "上場ETF（管理会社：JAMPファンド・マネジメント）に関する日々の開示事項",
      "pdf_url": "https://www.release.tdnet.info140120260630583959.pdf",
      "exchange": "東証",
      "markets": "",
      "source": "scraper",
      "category": "その他開示",
      "score": 35,
      "impact": "low",
      "direction": "unknown",
      "urgent": false,
      "confidence": 40,
      "is_correction": false,
      "tags": [],
      "reasons": [
        "その他開示"
      ],
      "summary": "定例・補足的な開示。株価への影響は限定的とみられる。",
      "analyzed_by": "rules",
      "analyzed_at": "2026-06-30T14:43:21+09:00"
    },
    {
      "id": "592c2fcb734b4bf8",
      "time": "2026-06-30T10:00:00+09:00",
      "code": "1329",
      "company": "Ｅ－ブラックロック",
      "title": "上場ETF（管理会社：ブラックロック・ジャパン）に関する日々の開示事項",
      "pdf_url": "https://www.release.tdnet.info140120260630584018.pdf",
      "exchange": "東証",
      "markets": "",
      "source": "scraper",
      "category": "その他開示",
      "score": 35,
      "impact": "low",
      "direction": "unknown",
      "urgent": false,
      "confidence": 40,
      "is_correction": false,
      "tags": [],
      "reasons": [
        "その他開示"
      ],
      "summary": "定例・補足的な開示。株価への影響は限定的とみられる。",
      "analyzed_by": "rules",
      "analyzed_at": "2026-06-30T14:43:21+09:00"
    },
    {
      "id": "f2822b97af65a12d",
      "time": "2026-06-30T10:00:00+09:00",
      "code": "1671",
      "company": "Ｅ－シンプレクス",
      "title": "上場ＥＴＦ(管理会社：シンプレクス・アセット・マネジメント)に関する日々の開示事項",
      "pdf_url": "https://www.release.tdnet.info140120260630583976.pdf",
      "exchange": "東証",
      "markets": "",
      "source": "scraper",
      "category": "その他開示",
      "score": 35,
      "impact": "low",
      "direction": "unknown",
      "urgent": false,
      "confidence": 40,
      "is_correction": false,
      "tags": [],
      "reasons": [
        "その他開示"
      ],
      "summary": "定例・補足的な開示。株価への影響は限定的とみられる。",
      "analyzed_by": "rules",
      "analyzed_at": "2026-06-30T14:43:21+09:00"
    },
    {
      "id": "1262576",
      "time": "2026-06-30T10:00:00+09:00",
      "code": "1329",
      "company": "Ｅ－ブラックロック",
      "title": "上場ETF（管理会社：ブラックロック・ジャパン）に関する日々の開示事項",
      "pdf_url": "https://webapi.yanoshin.jp/rd.php?https://www.release.tdnet.info/inbs/140120260630584018.pdf",
      "exchange": "東証",
      "markets": "",
      "source": "yanoshin",
      "category": "その他開示",
      "score": 35,
      "impact": "low",
      "direction": "unknown",
      "urgent": false,
      "confidence": 40,
      "is_correction": false,
      "tags": [],
      "reasons": [
        "その他開示"
      ],
      "summary": "定例・補足的な開示。株価への影響は限定的とみられる。",
      "analyzed_by": "rules",
      "analyzed_at": "2026-06-30T14:45:54+09:00"
    },
    {
      "id": "1262577",
      "time": "2026-06-30T10:00:00+09:00",
      "code": "1671",
      "company": "Ｅ－シンプレクス",
      "title": "上場ＥＴＦ(管理会社：シンプレクス・アセット・マネジメント)に関する日々の開示事項",
      "pdf_url": "https://webapi.yanoshin.jp/rd.php?https://www.release.tdnet.info/inbs/140120260630583976.pdf",
      "exchange": "東証",
      "markets": "",
      "source": "yanoshin",
      "category": "その他開示",
      "score": 35,
      "impact": "low",
      "direction": "unknown",
      "urgent": false,
      "confidence": 40,
      "is_correction": false,
      "tags": [],
      "reasons": [
        "その他開示"
      ],
      "summary": "定例・補足的な開示。株価への影響は限定的とみられる。",
      "analyzed_by": "rules",
      "analyzed_at": "2026-06-30T14:45:54+09:00"
    },
    {
      "id": "1262572",
      "time": "2026-06-30T08:30:00+09:00",
      "code": "1672",
      "company": "Ｅ－ＷｉｓｄｏｍＴｒ",
      "title": "上場ETF（管理会社：WisdomTree、外国投資法人：MSL）に関する日々の開示事項　",
      "pdf_url": "https://webapi.yanoshin.jp/rd.php?https://www.release.tdnet.info/inbs/140120260622575293.pdf",
      "exchange": "東証",
      "markets": "",
      "source": "yanoshin",
      "category": "その他開示",
      "score": 35,
      "impact": "low",
      "direction": "unknown",
      "urgent": false,
      "confidence": 40,
      "is_correction": false,
      "tags": [],
      "reasons": [
        "その他開示"
      ],
      "summary": "定例・補足的な開示。株価への影響は限定的とみられる。",
      "analyzed_by": "rules",
      "analyzed_at": "2026-06-30T14:45:54+09:00"
    },
    {
      "id": "1262573",
      "time": "2026-06-30T08:30:00+09:00",
      "code": "1672",
      "company": "Ｅ－ＷｉｓｄｏｍＴｒ",
      "title": "上場ETF（管理会社：WisdomTree、外国投資法人：CSL）に関する日々の開示事項　",
      "pdf_url": "https://webapi.yanoshin.jp/rd.php?https://www.release.tdnet.info/inbs/140120260630583934.pdf",
      "exchange": "東証",
      "markets": "",
      "source": "yanoshin",
      "category": "その他開示",
      "score": 35,
      "impact": "low",
      "direction": "unknown",
      "urgent": false,
      "confidence": 40,
      "is_correction": false,
      "tags": [],
      "reasons": [
        "その他開示"
      ],
      "summary": "定例・補足的な開示。株価への影響は限定的とみられる。",
      "analyzed_by": "rules",
      "analyzed_at": "2026-06-30T14:45:54+09:00"
    },
    {
      "id": "bfc0e73610192fb6",
      "time": "2026-06-30T08:30:00+09:00",
      "code": "1672",
      "company": "Ｅ－ＷｉｓｄｏｍＴｒ",
      "title": "上場ETF（管理会社：WisdomTree、外国投資法人：MSL）に関する日々の開示事項",
      "pdf_url": "https://www.release.tdnet.info140120260622575293.pdf",
      "exchange": "東証",
      "markets": "",
      "source": "scraper",
      "category": "その他開示",
      "score": 35,
      "impact": "low",
      "direction": "unknown",
      "urgent": false,
      "confidence": 40,
      "is_correction": false,
      "tags": [],
      "reasons": [
        "その他開示"
      ],
      "summary": "定例・補足的な開示。株価への影響は限定的とみられる。",
      "analyzed_by": "rules",
      "analyzed_at": "2026-06-30T14:43:21+09:00"
    },
    {
      "id": "be9c4d3fa889e480",
      "time": "2026-06-30T08:30:00+09:00",
      "code": "1672",
      "company": "Ｅ－ＷｉｓｄｏｍＴｒ",
      "title": "上場ETF（管理会社：WisdomTree、外国投資法人：CSL）に関する日々の開示事項",
      "pdf_url": "https://www.release.tdnet.info140120260630583934.pdf",
      "exchange": "東証",
      "markets": "",
      "source": "scraper",
      "category": "その他開示",
      "score": 35,
      "impact": "low",
      "direction": "unknown",
      "urgent": false,
      "confidence": 40,
      "is_correction": false,
      "tags": [],
      "reasons": [
        "その他開示"
      ],
      "summary": "定例・補足的な開示。株価への影響は限定的とみられる。",
      "analyzed_by": "rules",
      "analyzed_at": "2026-06-30T14:43:21+09:00"
    },
    {
      "id": "1262557",
      "time": "2026-06-30T08:00:00+09:00",
      "code": "506A",
      "company": "Ｐ－シンカナース",
      "title": "東京証券取引所 TOKYO PRO Marketへの上場目的の開示",
      "pdf_url": "https://webapi.yanoshin.jp/rd.php?https://www.release.tdnet.info/inbs/140120260629583889.pdf",
      "exchange": "東証",
      "markets": "",
      "source": "yanoshin",
      "category": "その他開示",
      "score": 35,
      "impact": "low",
      "direction": "unknown",
      "urgent": false,
      "confidence": 40,
      "is_correction": false,
      "tags": [],
      "reasons": [
        "その他開示"
      ],
      "summary": "定例・補足的な開示。株価への影響は限定的とみられる。",
      "analyzed_by": "rules",
      "analyzed_at": "2026-06-30T14:45:54+09:00"
    },
    {
      "id": "1262558",
      "time": "2026-06-30T08:00:00+09:00",
      "code": "5592",
      "company": "Ｇ－くすりの窓口",
      "title": "非上場の親会社等の決算に関するお知らせ",
      "pdf_url": "https://webapi.yanoshin.jp/rd.php?https://www.release.tdnet.info/inbs/140120260616571928.pdf",
      "exchange": "東証",
      "markets": "",
      "source": "yanoshin",
      "category": "その他開示",
      "score": 35,
      "impact": "low",
      "direction": "unknown",
      "urgent": false,
      "confidence": 40,
      "is_correction": false,
      "tags": [],
      "reasons": [
        "その他開示"
      ],
      "summary": "定例・補足的な開示。株価への影響は限定的とみられる。",
      "analyzed_by": "rules",
      "analyzed_at": "2026-06-30T14:45:54+09:00"
    },
    {
      "id": "1262560",
      "time": "2026-06-30T08:00:00+09:00",
      "code": "588A",
      "company": "Ｓ－アットマークテク",
      "title": "札幌証券取引所Sapporo PRO Frontier Market への上場のお知らせ",
      "pdf_url": "https://webapi.yanoshin.jp/rd.php?https://www.release.tdnet.info/inbs/140120260629582935.pdf",
      "exchange": "",
      "markets": "",
      "source": "yanoshin",
      "category": "その他開示",
      "score": 35,
      "impact": "low",
      "direction": "unknown",
      "urgent": false,
      "confidence": 40,
      "is_correction": false,
      "tags": [],
      "reasons": [
        "その他開示"
      ],
      "summary": "定例・補足的な開示。株価への影響は限定的とみられる。",
      "analyzed_by": "rules",
      "analyzed_at": "2026-06-30T14:45:54+09:00"
    },
    {
      "id": "1262561",
      "time": "2026-06-30T08:00:00+09:00",
      "code": "588A",
      "company": "Ｓ－アットマークテク",
      "title": "札幌証券取引所Sapporo PRO Frontier Marketへの上場に伴う当社決算情報等のお知らせ",
      "pdf_url": "https://webapi.yanoshin.jp/rd.php?https://www.release.tdnet.info/inbs/140120260629582946.pdf",
      "exchange": "",
      "markets": "",
      "source": "yanoshin",
      "category": "その他開示",
      "score": 35,
      "impact": "low",
      "direction": "unknown",
      "urgent": false,
      "confidence": 40,
      "is_correction": false,
      "tags": [],
      "reasons": [
        "その他開示"
      ],
      "summary": "定例・補足的な開示。株価への影響は限定的とみられる。",
      "analyzed_by": "rules",
      "analyzed_at": "2026-06-30T14:45:54+09:00"
    },
    {
      "id": "1262562",
      "time": "2026-06-30T08:00:00+09:00",
      "code": "588A",
      "company": "Ｓ－アットマークテク",
      "title": "流動性プロバイダー指定のお知らせ",
      "pdf_url": "https://webapi.yanoshin.jp/rd.php?https://www.release.tdnet.info/inbs/140120260629582948.pdf",
      "exchange": "",
      "markets": "",
      "source": "yanoshin",
      "category": "その他開示",
      "score": 35,
      "impact": "low",
      "direction": "unknown",
      "urgent": false,
      "confidence": 40,
      "is_correction": false,
      "tags": [],
      "reasons": [
        "その他開示"
      ],
      "summary": "定例・補足的な開示。株価への影響は限定的とみられる。",
      "analyzed_by": "rules",
      "analyzed_at": "2026-06-30T14:45:54+09:00"
    },
    {
      "id": "1262563",
      "time": "2026-06-30T08:00:00+09:00",
      "code": "588A",
      "company": "Ｓ－アットマークテク",
      "title": "札幌証券取引所Sapporo PRO Frontier Market への上場目的の開示に関するお知らせ",
      "pdf_url": "https://webapi.yanoshin.jp/rd.php?https://www.release.tdnet.info/inbs/140120260629582952.pdf",
      "exchange": "",
      "markets": "",
      "source": "yanoshin",
      "category": "その他開示",
      "score": 35,
      "impact": "low",
      "direction": "unknown",
      "urgent": false,
      "confidence": 40,
      "is_correction": false,
      "tags": [],
      "reasons": [
        "その他開示"
      ],
      "summary": "定例・補足的な開示。株価への影響は限定的とみられる。",
      "analyzed_by": "rules",
      "analyzed_at": "2026-06-30T14:45:54+09:00"
    },
    {
      "id": "1262565",
      "time": "2026-06-30T08:00:00+09:00",
      "code": "589A",
      "company": "Ｇ－ネイス",
      "title": "東京証券取引所グロース市場への上場に伴う当社決算情報等のお知らせ",
      "pdf_url": "https://webapi.yanoshin.jp/rd.php?https://www.release.tdnet.info/inbs/140120260626581345.pdf",
      "exchange": "東証",
      "markets": "",
      "source": "yanoshin",
      "category": "その他開示",
      "score": 35,
      "impact": "low",
      "direction": "unknown",
      "urgent": false,
      "confidence": 40,
      "is_correction": false,
      "tags": [],
      "reasons": [
        "その他開示"
      ],
      "summary": "定例・補足的な開示。株価への影響は限定的とみられる。",
      "analyzed_by": "rules",
      "analyzed_at": "2026-06-30T14:45:54+09:00"
    },
    {
      "id": "1262566",
      "time": "2026-06-30T08:00:00+09:00",
      "code": "589A",
      "company": "Ｇ－ネイス",
      "title": "親会社以外の支配株主及び主要株主の異動に関するお知らせ",
      "pdf_url": "https://webapi.yanoshin.jp/rd.php?https://www.release.tdnet.info/inbs/140120260626581356.pdf",
      "exchange": "東証",
      "markets": "",
      "source": "yanoshin",
      "category": "大株主異動",
      "score": 62,
      "impact": "medium",
      "direction": "unknown",
      "urgent": false,
      "confidence": 65,
      "is_correction": false,
      "tags": [],
      "reasons": [
        "主要株主の異動"
      ],
      "summary": "主要株主・親会社の異動。支配構造の変化。",
      "analyzed_by": "rules",
      "analyzed_at": "2026-06-30T14:45:54+09:00"
    },
    {
      "id": "1262567",
      "time": "2026-06-30T08:00:00+09:00",
      "code": "595A",
      "company": "Ｐ－不二興産",
      "title": "東京証券取引所 TOKYO PRO Marketへの上場のお知らせ",
      "pdf_url": "https://webapi.yanoshin.jp/rd.php?https://www.release.tdnet.info/inbs/140120260629583026.pdf",
      "exchange": "東証",
      "markets": "",
      "source": "yanoshin",
      "category": "その他開示",
      "score": 35,
      "impact": "low",
      "direction": "unknown",
      "urgent": false,
      "confidence": 40,
      "is_correction": false,
      "tags": [],
      "reasons": [
        "その他開示"
      ],
      "summary": "定例・補足的な開示。株価への影響は限定的とみられる。",
      "analyzed_by": "rules",
      "analyzed_at": "2026-06-30T14:45:54+09:00"
    },
    {
      "id": "1262568",
      "time": "2026-06-30T08:00:00+09:00",
      "code": "595A",
      "company": "Ｐ－不二興産",
      "title": "東京証券取引所 TOKYO PRO Marketへの上場に伴う当社決算情報等のお知らせ",
      "pdf_url": "https://webapi.yanoshin.jp/rd.php?https://www.release.tdnet.info/inbs/140120260629583046.pdf",
      "exchange": "東証",
      "markets": "",
      "source": "yanoshin",
      "category": "その他開示",
      "score": 35,
      "impact": "low",
      "direction": "unknown",
      "urgent": false,
      "confidence": 40,
      "is_correction": false,
      "tags": [],
      "reasons": [
        "その他開示"
      ],
      "summary": "定例・補足的な開示。株価への影響は限定的とみられる。",
      "analyzed_by": "rules",
      "analyzed_at": "2026-06-30T14:45:54+09:00"
    },
    {
      "id": "1262569",
      "time": "2026-06-30T08:00:00+09:00",
      "code": "595A",
      "company": "Ｐ－不二興産",
      "title": "流動性プロバイダーの指定のお知らせ",
      "pdf_url": "https://webapi.yanoshin.jp/rd.php?https://www.release.tdnet.info/inbs/140120260629583059.pdf",
      "exchange": "東証",
      "markets": "",
      "source": "yanoshin",
      "category": "その他開示",
      "score": 35,
      "impact": "low",
      "direction": "unknown",
      "urgent": false,
      "confidence": 40,
      "is_correction": false,
      "tags": [],
      "reasons": [
        "その他開示"
      ],
      "summary": "定例・補足的な開示。株価への影響は限定的とみられる。",
      "analyzed_by": "rules",
      "analyzed_at": "2026-06-30T14:45:54+09:00"
    },
    {
      "id": "1262570",
      "time": "2026-06-30T08:00:00+09:00",
      "code": "595A",
      "company": "Ｐ－不二興産",
      "title": "東京証券取引所 TOKYO PRO Marketへの上場目的の開示について",
      "pdf_url": "https://webapi.yanoshin.jp/rd.php?https://www.release.tdnet.info/inbs/140120260629583077.pdf",
      "exchange": "東証",
      "markets": "",
      "source": "yanoshin",
      "category": "その他開示",
      "score": 35,
      "impact": "low",
      "direction": "unknown",
      "urgent": false,
      "confidence": 40,
      "is_correction": false,
      "tags": [],
      "reasons": [
        "その他開示"
      ],
      "summary": "定例・補足的な開示。株価への影響は限定的とみられる。",
      "analyzed_by": "rules",
      "analyzed_at": "2026-06-30T14:45:54+09:00"
    },
    {
      "id": "b70390dc63420de1",
      "time": "2026-06-30T08:00:00+09:00",
      "code": "506A",
      "company": "Ｐ－シンカナース",
      "title": "東京証券取引所 TOKYO PRO Marketへの上場目的の開示",
      "pdf_url": "https://www.release.tdnet.info140120260629583889.pdf",
      "exchange": "東証",
      "markets": "",
      "source": "scraper",
      "category": "その他開示",
      "score": 35,
      "impact": "low",
      "direction": "unknown",
      "urgent": false,
      "confidence": 40,
      "is_correction": false,
      "tags": [],
      "reasons": [
        "その他開示"
      ],
      "summary": "定例・補足的な開示。株価への影響は限定的とみられる。",
      "analyzed_by": "rules",
      "analyzed_at": "2026-06-30T14:43:21+09:00"
    },
    {
      "id": "f24d16a2cc51c8f9",
      "time": "2026-06-30T08:00:00+09:00",
      "code": "5592",
      "company": "Ｇ－くすりの窓口",
      "title": "非上場の親会社等の決算に関するお知らせ",
      "pdf_url": "https://www.release.tdnet.info140120260616571928.pdf",
      "exchange": "東証",
      "markets": "",
      "source": "scraper",
      "category": "その他開示",
      "score": 35,
      "impact": "low",
      "direction": "unknown",
      "urgent": false,
      "confidence": 40,
      "is_correction": false,
      "tags": [],
      "reasons": [
        "その他開示"
      ],
      "summary": "定例・補足的な開示。株価への影響は限定的とみられる。",
      "analyzed_by": "rules",
      "analyzed_at": "2026-06-30T14:43:21+09:00"
    },
    {
      "id": "1345730124bdc164",
      "time": "2026-06-30T08:00:00+09:00",
      "code": "588A",
      "company": "Ｓ－アットマークテク",
      "title": "札幌証券取引所Sapporo PRO Frontier Market への上場のお知らせ",
      "pdf_url": "https://www.release.tdnet.info140120260629582935.pdf",
      "exchange": "東証",
      "markets": "",
      "source": "scraper",
      "category": "その他開示",
      "score": 35,
      "impact": "low",
      "direction": "unknown",
      "urgent": false,
      "confidence": 40,
      "is_correction": false,
      "tags": [],
      "reasons": [
        "その他開示"
      ],
      "summary": "定例・補足的な開示。株価への影響は限定的とみられる。",
      "analyzed_by": "rules",
      "analyzed_at": "2026-06-30T14:43:21+09:00"
    },
    {
      "id": "2746092974c307fb",
      "time": "2026-06-30T08:00:00+09:00",
      "code": "588A",
      "company": "Ｓ－アットマークテク",
      "title": "札幌証券取引所Sapporo PRO Frontier Marketへの上場に伴う当社決算情報等のお知らせ",
      "pdf_url": "https://www.release.tdnet.info140120260629582946.pdf",
      "exchange": "東証",
      "markets": "",
      "source": "scraper",
      "category": "その他開示",
      "score": 35,
      "impact": "low",
      "direction": "unknown",
      "urgent": false,
      "confidence": 40,
      "is_correction": false,
      "tags": [],
      "reasons": [
        "その他開示"
      ],
      "summary": "定例・補足的な開示。株価への影響は限定的とみられる。",
      "analyzed_by": "rules",
      "analyzed_at": "2026-06-30T14:43:21+09:00"
    },
    {
      "id": "fccd5e0443eb1e4f",
      "time": "2026-06-30T08:00:00+09:00",
      "code": "588A",
      "company": "Ｓ－アットマークテク",
      "title": "流動性プロバイダー指定のお知らせ",
      "pdf_url": "https://www.release.tdnet.info140120260629582948.pdf",
      "exchange": "東証",
      "markets": "",
      "source": "scraper",
      "category": "その他開示",
      "score": 35,
      "impact": "low",
      "direction": "unknown",
      "urgent": false,
      "confidence": 40,
      "is_correction": false,
      "tags": [],
      "reasons": [
        "その他開示"
      ],
      "summary": "定例・補足的な開示。株価への影響は限定的とみられる。",
      "analyzed_by": "rules",
      "analyzed_at": "2026-06-30T14:43:21+09:00"
    },
    {
      "id": "52f710e99018b9d1",
      "time": "2026-06-30T08:00:00+09:00",
      "code": "588A",
      "company": "Ｓ－アットマークテク",
      "title": "札幌証券取引所Sapporo PRO Frontier Market への上場目的の開示に関するお知らせ",
      "pdf_url": "https://www.release.tdnet.info140120260629582952.pdf",
      "exchange": "東証",
      "markets": "",
      "source": "scraper",
      "category": "その他開示",
      "score": 35,
      "impact": "low",
      "direction": "unknown",
      "urgent": false,
      "confidence": 40,
      "is_correction": false,
      "tags": [],
      "reasons": [
        "その他開示"
      ],
      "summary": "定例・補足的な開示。株価への影響は限定的とみられる。",
      "analyzed_by": "rules",
      "analyzed_at": "2026-06-30T14:43:21+09:00"
    },
    {
      "id": "1c7f89d04ba7826d",
      "time": "2026-06-30T08:00:00+09:00",
      "code": "589A",
      "company": "Ｇ－ネイス",
      "title": "東京証券取引所グロース市場への上場に伴う当社決算情報等のお知らせ",
      "pdf_url": "https://www.release.tdnet.info140120260626581345.pdf",
      "exchange": "東証",
      "markets": "",
      "source": "scraper",
      "category": "その他開示",
      "score": 35,
      "impact": "low",
      "direction": "unknown",
      "urgent": false,
      "confidence": 40,
      "is_correction": false,
      "tags": [],
      "reasons": [
        "その他開示"
      ],
      "summary": "定例・補足的な開示。株価への影響は限定的とみられる。",
      "analyzed_by": "rules",
      "analyzed_at": "2026-06-30T14:43:21+09:00"
    },
    {
      "id": "129e8515b10694d4",
      "time": "2026-06-30T08:00:00+09:00",
      "code": "589A",
      "company": "Ｇ－ネイス",
      "title": "親会社以外の支配株主及び主要株主の異動に関するお知らせ",
      "pdf_url": "https://www.release.tdnet.info140120260626581356.pdf",
      "exchange": "東証",
      "markets": "",
      "source": "scraper",
      "category": "大株主異動",
      "score": 62,
      "impact": "medium",
      "direction": "unknown",
      "urgent": false,
      "confidence": 65,
      "is_correction": false,
      "tags": [],
      "reasons": [
        "主要株主の異動"
      ],
      "summary": "主要株主・親会社の異動。支配構造の変化。",
      "analyzed_by": "rules",
      "analyzed_at": "2026-06-30T14:43:21+09:00"
    },
    {
      "id": "7d91f51a0b3aa38f",
      "time": "2026-06-30T08:00:00+09:00",
      "code": "595A",
      "company": "Ｐ－不二興産",
      "title": "東京証券取引所 TOKYO PRO Marketへの上場のお知らせ",
      "pdf_url": "https://www.release.tdnet.info140120260629583026.pdf",
      "exchange": "東証",
      "markets": "",
      "source": "scraper",
      "category": "その他開示",
      "score": 35,
      "impact": "low",
      "direction": "unknown",
      "urgent": false,
      "confidence": 40,
      "is_correction": false,
      "tags": [],
      "reasons": [
        "その他開示"
      ],
      "summary": "定例・補足的な開示。株価への影響は限定的とみられる。",
      "analyzed_by": "rules",
      "analyzed_at": "2026-06-30T14:43:21+09:00"
    },
    {
      "id": "744be7313434dce7",
      "time": "2026-06-30T08:00:00+09:00",
      "code": "595A",
      "company": "Ｐ－不二興産",
      "title": "東京証券取引所 TOKYO PRO Marketへの上場に伴う当社決算情報等のお知らせ",
      "pdf_url": "https://www.release.tdnet.info140120260629583046.pdf",
      "exchange": "東証",
      "markets": "",
      "source": "scraper",
      "category": "その他開示",
      "score": 35,
      "impact": "low",
      "direction": "unknown",
      "urgent": false,
      "confidence": 40,
      "is_correction": false,
      "tags": [],
      "reasons": [
        "その他開示"
      ],
      "summary": "定例・補足的な開示。株価への影響は限定的とみられる。",
      "analyzed_by": "rules",
      "analyzed_at": "2026-06-30T14:43:21+09:00"
    },
    {
      "id": "57e3b84dcf9911ab",
      "time": "2026-06-30T08:00:00+09:00",
      "code": "595A",
      "company": "Ｐ－不二興産",
      "title": "流動性プロバイダーの指定のお知らせ",
      "pdf_url": "https://www.release.tdnet.info140120260629583059.pdf",
      "exchange": "東証",
      "markets": "",
      "source": "scraper",
      "category": "その他開示",
      "score": 35,
      "impact": "low",
      "direction": "unknown",
      "urgent": false,
      "confidence": 40,
      "is_correction": false,
      "tags": [],
      "reasons": [
        "その他開示"
      ],
      "summary": "定例・補足的な開示。株価への影響は限定的とみられる。",
      "analyzed_by": "rules",
      "analyzed_at": "2026-06-30T14:43:21+09:00"
    },
    {
      "id": "d3e21956934505d7",
      "time": "2026-06-30T08:00:00+09:00",
      "code": "595A",
      "company": "Ｐ－不二興産",
      "title": "東京証券取引所 TOKYO PRO Marketへの上場目的の開示について",
      "pdf_url": "https://www.release.tdnet.info140120260629583077.pdf",
      "exchange": "東証",
      "markets": "",
      "source": "scraper",
      "category": "その他開示",
      "score": 35,
      "impact": "low",
      "direction": "unknown",
      "urgent": false,
      "confidence": 40,
      "is_correction": false,
      "tags": [],
      "reasons": [
        "その他開示"
      ],
      "summary": "定例・補足的な開示。株価への影響は限定的とみられる。",
      "analyzed_by": "rules",
      "analyzed_at": "2026-06-30T14:43:21+09:00"
    }
  ]
}